datedetect/__init__.py
datedetect/datedetect.py
datedetect/exceptions.py
datedetect/utils.py
datedetect-1.0.0.dist-info/METADATA
datedetect-1.0.0.dist-info/WHEEL
datedetect-1.0.0.dist-info/top_level.txt
datedetect-1.0.0.dist-info/RECORD
