Metadata-Version: 2.1
Name: datedetect
Version: 1.0.0
Summary: Get possible string format codes of the given datetime object.
Home-page: https://github.com/ash-ishh/datedetect
Author: Ash-Ishh..
Author-email: mr.akc@outlook.com
License: UNKNOWN
Platform: UNKNOWN
Requires-Python: >=3.6
